pkicompose/__init__.py
pkicompose/__main__.py
pkicompose/cli.py
pkicompose/pkicompose.py
pkicompose-0.0.1.dist-info/LICENSE
pkicompose-0.0.1.dist-info/METADATA
pkicompose-0.0.1.dist-info/WHEEL
pkicompose-0.0.1.dist-info/entry_points.txt
pkicompose-0.0.1.dist-info/top_level.txt
pkicompose-0.0.1.dist-info/RECORD
